cauldron_ml/__init__.py
cauldron_ml/__main__.py
cauldron_ml/cli.py
cauldron_ml/cli_oop.py
cauldron_ml/config.py
cauldron_ml/docker/BaseDockerfile
cauldron_ml/docker/Dockerfile
cauldron_ml/exceptions.py
cauldron_ml/prompts.py
cauldron_ml/templates/penguin_example/build/ci_workflow.env
cauldron_ml/templates/penguin_example/build/project_requirements.txt
cauldron_ml/templates/penguin_example/model/__init__.py
cauldron_ml/templates/penguin_example/model/components.py
cauldron_ml/templates/penguin_example/model/config/inputs.json
cauldron_ml/templates/penguin_example/model/models.py
cauldron_ml/templates/penguin_example/model/predict.py
cauldron_ml/templates/penguin_example/model/run.py
cauldron_ml/templates/penguin_example/model/tests/test_main.py
cauldron_ml/test_models.py
cauldron_ml/test_prefix.sh
cauldron_ml/vertex.py
cauldron_ml-0.6.2.dist-info/METADATA
cauldron_ml-0.6.2.dist-info/WHEEL
cauldron_ml-0.6.2.dist-info/entry_points.txt
cauldron_ml-0.6.2.dist-info/RECORD
