Metadata-Version: 2.1
Name: cauldron-ml
Version: 0.6.2
Summary: A CLI tool for building and deploying Kubeflow Pipelines in GCP Vertex AI
Author: Darren Price
Author-email: darren.price@moneysupermarket.com
Requires-Python: >=3.10,<4.0
Classifier: Programming Language :: Python :: 3
Classifier: Programming Language :: Python :: 3.10
Classifier: Programming Language :: Python :: 3.11
Classifier: Programming Language :: Python :: 3.12
Requires-Dist: google-cloud-aiplatform (>=1.65.0,<2.0.0)
Requires-Dist: kfp (>=2.9.0,<3.0.0)
Requires-Dist: pyyaml (>=6.0.0,<7.0.0)
Requires-Dist: typer (>=0.12.0,<1.0.0)
